bidon/__init__.py
bidon/__main__.py
poc_bidon-0.0.0.dist-info/METADATA
poc_bidon-0.0.0.dist-info/RECORD
poc_bidon-0.0.0.dist-info/WHEEL
poc_bidon-0.0.0.dist-info/entry_points.txt
poc_bidon-0.0.0.dist-info/pbr.json
poc_bidon-0.0.0.dist-info/top_level.txt
