Metadata-Version: 2.1
Name: poc-bidon
Version: 0.0.0
Summary: test project
Home-page: https://github.com/4383/poc-bidon
Author: Hervé Beraud
Author-email: herveberaud.pro@gmail.com
License: UNKNOWN
Platform: UNKNOWN
Classifier: Development Status :: 5 - Production/Stable
Classifier: Intended Audience :: Information Technology
Classifier: License :: OSI Approved :: MIT License
Classifier: Operating System :: POSIX
Classifier: Programming Language :: Python
Classifier: Programming Language :: Python :: 2
Classifier: Programming Language :: Python :: 2.7
Classifier: Programming Language :: Python :: 3
Classifier: Programming Language :: Python :: 3.4
Classifier: Programming Language :: Python :: 3.5
Classifier: Programming Language :: Python :: 3.6
Requires: pbd
Provides-Extra: test
Provides-Extra: devel
Requires-Dist: PyYAML
Requires-Dist: future
Provides-Extra: devel
Requires-Dist: fixtures; extra == 'devel'
Requires-Dist: pbr; extra == 'devel'
Requires-Dist: tox; extra == 'devel'
Provides-Extra: test
Requires-Dist: fixtures; extra == 'test'
Requires-Dist: tox; extra == 'test'
